colab_toolbox/__init__.py
colab_toolbox/colabtool.py
colab_toolbox/auth/__init__.py
colab_toolbox/auth/google.py
colab_toolbox/common/__init__.py
colab_toolbox/common/utils.py
colab_toolbox/convert/__init__.py
colab_toolbox/convert/ocr_tool.py
colab_toolbox/ext/__init__.py
colab_toolbox/io/__init__.py
colab_toolbox/io/gsheets.py
colab_toolbox/script/__init__.py
colab_toolbox/script/cleanup.py
colab_toolbox/script/setup_ocrmypdf.sh
colab_toolbox/script/setup_pytesseract.sh
colab_toolbox/script/setup_quarto.sh
colab_toolbox/script/setup_selenium.sh
colab_toolbox/script/setup_talib.sh
colab_toolbox/script/setup_xterm.sh
colab_toolbox/sync/__init__.py
colab_toolbox/sync/gittool.py
colab_toolbox-0.1.4.dist-info/METADATA
colab_toolbox-0.1.4.dist-info/WHEEL
colab_toolbox-0.1.4.dist-info/entry_points.txt
colab_toolbox-0.1.4.dist-info/top_level.txt
colab_toolbox-0.1.4.dist-info/RECORD
