Metadata-Version: 2.1
Name: colab_toolbox
Version: 0.1.4
Summary: Effortlessly set up and configure multiple tools for Google Colab without the need for shell commands or extensive coding.
Home-page: https://github.com/thinh-vu/colab_toolbox
Author: Thinh Vu
Author-email: vnstock-hq@gmail.com
License: MIT
Classifier: License :: OSI Approved :: MIT License
Classifier: Programming Language :: Python :: 3
Classifier: Programming Language :: Python :: 3.7
Classifier: Programming Language :: Python :: 3.8
Classifier: Programming Language :: Python :: 3.9
Classifier: Programming Language :: Python :: 3.10
Classifier: Programming Language :: Python :: 3.11
Classifier: Operating System :: OS Independent
